profusion/__init__.py
profusion/bloom.py
profusion/counting_bloom.py
profusion/mmapped_counting_bloom.py
profusion/scalable_bloom.py
profusion-0.1.3.dist-info/LICENSE
profusion-0.1.3.dist-info/METADATA
profusion-0.1.3.dist-info/WHEEL
profusion-0.1.3.dist-info/top_level.txt
profusion-0.1.3.dist-info/RECORD
